{
	"variables": [],
	"info": {
		"name": "idOS",
		"_postman_id": "f0fd9007-59fa-532f-ff34-4ea173a79e21",
		"description": "",
		"schema": "https://schema.getpostman.com/json/collection/v2.0.0/collection.json"
	},
	"item": [
		{
			"name": "Company",
			"description": "",
			"item": [
				{
					"name": "Company | listAll",
					"request": {
						"url": "{{URL}}companies?companyPrivKey=4e37dae79456985ae0d27a67639cf335",
						"method": "GET",
						"header": [],
						"body": {
							"mode": "formdata",
							"formdata": []
						},
						"description": "GET /companies/"
					},
					"response": []
				},
				{
					"name": "Company | getOne",
					"request": {
						"url": "{{URL}}companies/veridu-ltd?companyPrivKey=4e37dae79456985ae0d27a67639cf335",
						"method": "GET",
						"header": [],
						"body": {
							"mode": "formdata",
							"formdata": []
						},
						"description": "GET /companies/{companySlug}"
					},
					"response": []
				},
				{
					"name": "Company | createNew",
					"request": {
						"url": "{{URL}}companies?companyPrivKey=4e37dae79456985ae0d27a67639cf335",
						"method": "POST",
						"header": [
							{
								"key": "Content-Type",
								"value": "application/json",
								"description": ""
							}
						],
						"body": {
							"mode": "raw",
							"raw": "{\n    \"name\": \"Melan Ltd.\"\n}"
						},
						"description": "POST /companies/"
					},
					"response": []
				},
				{
					"name": "Company | updateOne",
					"request": {
						"url": "{{URL}}companies/veridu-ltd?companyPrivKey=4e37dae79456985ae0d27a67639cf335",
						"method": "PUT",
						"header": [
							{
								"key": "Content-Type",
								"value": "application/json",
								"description": ""
							}
						],
						"body": {
							"mode": "raw",
							"raw": "{\n    \"name\": \"Veridu Ltd.\"\n}"
						},
						"description": "PUT /companies/{companySlug}"
					},
					"response": []
				},
				{
					"name": "Company | deleteOne",
					"request": {
						"url": "{{URL}}companies/app-deck?companyPrivKey=4e37dae79456985ae0d27a67639cf335",
						"method": "DELETE",
						"header": [],
						"body": {
							"mode": "formdata",
							"formdata": []
						},
						"description": "DELETE /companies/{companySlug}"
					},
					"response": []
				}
			]
		},
		{
			"name": "Company\\Credential",
			"description": "",
			"item": [
				{
					"name": "Credential | listAll",
					"request": {
						"url": "{{URL}}companies/veridu-ltd/credentials?companyPrivKey=4e37dae79456985ae0d27a67639cf335",
						"method": "GET",
						"header": [],
						"body": {
							"mode": "formdata",
							"formdata": []
						},
						"description": "GET /companies/{companySlug}/credentials    "
					},
					"response": []
				},
				{
					"name": "Credential | getOne",
					"request": {
						"url": "{{URL}}companies/veridu-ltd/credentials/4c9184f37cff01bcdc32dc486ec36961?companyPrivKey=4e37dae79456985ae0d27a67639cf335",
						"method": "GET",
						"header": [],
						"body": {
							"mode": "formdata",
							"formdata": []
						},
						"description": "GET /companies/{companySlug}/credentials/{credentialPubKey}"
					},
					"response": []
				},
				{
					"name": "Credential | createNew",
					"request": {
						"url": "{{URL}}companies/veridu-ltd/credentials?companyPrivKey=4e37dae79456985ae0d27a67639cf335",
						"method": "POST",
						"header": [
							{
								"key": "Content-Type",
								"value": "application/json",
								"description": ""
							}
						],
						"body": {
							"mode": "raw",
							"raw": "{\n    \"name\": \"Very Secure\",\n    \"production\": false\n}"
						},
						"description": "POST /companies/{companySlug}/credentials"
					},
					"response": []
				},
				{
					"name": "Credential | updateOne",
					"request": {
						"url": "{{URL}}companies/veridu-ltd/credentials/def000002fd40ba783c1737a31ffd9024482c2b90cce9c720b6e24b5cec191166e8feb3a72dec2f15329fcafc8f543f310f21c354ab52c4e77a704ed6a54befc8856312c?companyPrivKey=4e37dae79456985ae0d27a67639cf335",
						"method": "PUT",
						"header": [
							{
								"key": "Content-Type",
								"value": "application/json",
								"description": ""
							}
						],
						"body": {
							"mode": "raw",
							"raw": "{\n    \"name\": \"My Test Key\"\n}"
						},
						"description": "PUT /companies/{companySlug}/credentials/{credentialPubKey}"
					},
					"response": []
				},
				{
					"name": "Credential | deleteOne",
					"request": {
						"url": "{{URL}}companies/veridu-ltd/credentials/def000002fd40ba783c1737a31ffd9024482c2b90cce9c720b6e24b5cec191166e8feb3a72dec2f15329fcafc8f543f310f21c354ab52c4e77a704ed6a54befc8856312c?companyPrivKey=4e37dae79456985ae0d27a67639cf335",
						"method": "DELETE",
						"header": [],
						"body": {
							"mode": "raw",
							"raw": ""
						},
						"description": "DELETE /companies/{companySlug}/credentials/{credentialPubKey}"
					},
					"response": []
				}
			]
		},
		{
			"name": "Company\\Permissions",
			"description": "",
			"item": [
				{
					"name": "Permissions | listAll",
					"request": {
						"url": "{{URL}}companies/veridu-ltd/permissions?companyPrivKey=4e37dae79456985ae0d27a67639cf335",
						"method": "GET",
						"header": [],
						"body": {
							"mode": "formdata",
							"formdata": []
						},
						"description": "GET /companies/{companySlug}/permissions    "
					},
					"response": []
				},
				{
					"name": "Permissions | get One",
					"request": {
						"url": "{{URL}}companies/veridu-ltd/permissions/companies:createNew?companyPrivKey=4e37dae79456985ae0d27a67639cf335",
						"method": "GET",
						"header": [],
						"body": {
							"mode": "formdata",
							"formdata": []
						},
						"description": "GET /companies/{companySlug}/permissions/{routeName}"
					},
					"response": []
				},
				{
					"name": "Permissions | createNew",
					"request": {
						"url": "{{URL}}companies/veridu-ltd/permissions?companyPrivKey=4e37dae79456985ae0d27a67639cf335",
						"method": "POST",
						"header": [
							{
								"key": "Content-Type",
								"value": "application/json",
								"description": ""
							}
						],
						"body": {
							"mode": "raw",
							"raw": "{\n    \"routeName\": \"credential:getOne\"\n}"
						},
						"description": "POST /companies/{companySlug}/permissions"
					},
					"response": []
				},
				{
					"name": "Permissions | deleteOne",
					"request": {
						"url": "{{URL}}companies/veridu-ltd/permissions/credential:getOne?companyPrivKey=4e37dae79456985ae0d27a67639cf335",
						"method": "DELETE",
						"header": [],
						"body": {
							"mode": "raw",
							"raw": ""
						},
						"description": "DELETE /companies/{companySlug}/permissions/{routeName}"
					},
					"response": []
				},
				{
					"name": "Permissions | deleteAll",
					"request": {
						"url": "{{URL}}companies/veridu-ltd/permissions?companyPrivKey=4e37dae79456985ae0d27a67639cf335",
						"method": "DELETE",
						"header": [],
						"body": {
							"mode": "raw",
							"raw": ""
						},
						"description": "DELETE /companies/{companySlug}/permissions"
					},
					"response": []
				}
			]
		},
		{
			"name": "Company\\Settings",
			"description": "",
			"item": [
				{
					"name": "Settings | listAll",
					"request": {
						"url": "{{URL}}companies/veridu-ltd/settings?companyPrivKey=4e37dae79456985ae0d27a67639cf335",
						"method": "GET",
						"header": [],
						"body": {
							"mode": "formdata",
							"formdata": []
						},
						"description": "GET /companies/{companySlug}/settings    "
					},
					"response": []
				},
				{
					"name": "Settings | get All from section",
					"request": {
						"url": "{{URL}}companies/veridu-ltd/settings/et?companyPrivKey=4e37dae79456985ae0d27a67639cf335",
						"method": "GET",
						"header": [],
						"body": {
							"mode": "formdata",
							"formdata": []
						},
						"description": "GET /companies/{companySlug}/segttings/{section}"
					},
					"response": []
				},
				{
					"name": "Settings | get One",
					"request": {
						"url": "{{URL}}companies/veridu-ltd/settings/et/minima?companyPrivKey=4e37dae79456985ae0d27a67639cf335",
						"method": "GET",
						"header": [],
						"body": {
							"mode": "formdata",
							"formdata": []
						},
						"description": "GET /companies/{companySlug}/segttings/{section}/{property}"
					},
					"response": []
				},
				{
					"name": "Settings | createNew",
					"request": {
						"url": "{{URL}}companies/veridu-ltd/settings?companyPrivKey=4e37dae79456985ae0d27a67639cf335",
						"method": "POST",
						"header": [
							{
								"key": "Content-Type",
								"value": "application/json",
								"description": ""
							}
						],
						"body": {
							"mode": "raw",
							"raw": "{\n    \"section\": \"velita\",\n    \"property\": \"bicxuitoa\",\n    \"value\": \"biscuit\"\n}"
						},
						"description": "POST /companies/{companySlug}/settings"
					},
					"response": []
				},
				{
					"name": "Settings | updateOne",
					"request": {
						"url": "{{URL}}companies/veridu-ltd/settings/et/minima?companyPrivKey=4e37dae79456985ae0d27a67639cf335",
						"method": "PUT",
						"header": [
							{
								"key": "Content-Type",
								"value": "application/json",
								"description": ""
							}
						],
						"body": {
							"mode": "raw",
							"raw": "{\n    \"value\": \"New Prop value\"\n}"
						},
						"description": "PUT /companies/{companySlug}/settings/{section}/{property}"
					},
					"response": []
				},
				{
					"name": "Settings | deleteOne",
					"request": {
						"url": "{{URL}}companies/veridu-ltd/settings/et/minima?companyPrivKey=4e37dae79456985ae0d27a67639cf335",
						"method": "DELETE",
						"header": [],
						"body": {
							"mode": "raw",
							"raw": ""
						},
						"description": "DELETE /companies/{companySlug}/settings/{section}/{property}"
					},
					"response": []
				},
				{
					"name": "Settings | deleteAll",
					"request": {
						"url": "{{URL}}companies/veridu-ltd/settings?companyPrivKey=4e37dae79456985ae0d27a67639cf335",
						"method": "DELETE",
						"header": [],
						"body": {
							"mode": "raw",
							"raw": ""
						},
						"description": "DELETE /companies/{companySlug}/settings"
					},
					"response": []
				}
			]
		},
		{
			"name": "Endpoints",
			"request": {
				"url": "{{URL}}",
				"method": "GET",
				"header": [],
				"body": {
					"mode": "raw",
					"raw": ""
				},
				"description": "GET /"
			},
			"response": []
		}
	]
}